nifstd_tools/__init__.py
nifstd_tools/aba_uberon.py
nifstd_tools/allen_transgenic_lines.py
nifstd_tools/chebi_bridge.py
nifstd_tools/chebi_slim.py
nifstd_tools/docs.py
nifstd_tools/doid_slim.py
nifstd_tools/dumpnlx.py
nifstd_tools/extracting_pmids_from_neurolex.py
nifstd_tools/fma_slim.py
nifstd_tools/fragment_map.py
nifstd_tools/gen_nat_models.py
nifstd_tools/hbp_merge.py
nifstd_tools/hbp_parc_output.py
nifstd_tools/ksdesc_bridge.py
nifstd_tools/map-identifiers.py
nifstd_tools/mapnlxilx.py
nifstd_tools/ncbigene_slim.py
nifstd_tools/nif_cell.py
nifstd_tools/nifgafix.py
nifstd_tools/ontree.py
nifstd_tools/ontree_server.py
nifstd_tools/scr_sync.py
nifstd_tools/sheets.py
nifstd_tools/sheets_sparc.py
nifstd_tools/simplify.py
nifstd_tools/slimgen.py
nifstd_tools/utils.py
nifstd_tools-0.0.7.data/data/share/nifstd/resources/26451489 table 1.csv
nifstd_tools-0.0.7.data/data/share/nifstd/resources/doc-config.yaml
nifstd_tools-0.0.7.data/data/share/nifstd/resources/docs-init.el
nifstd_tools-0.0.7.data/data/share/nifstd/resources/neuron_phenotype.csv
nifstd_tools-0.0.7.data/data/share/nifstd/resources/neuron_phenotype_edges.csv
nifstd_tools-0.0.7.data/data/share/nifstd/resources/sparc_term_versions/sparc_terms2-mod.txt
nifstd_tools-0.0.7.data/scripts/ttlcmp
nifstd_tools-0.0.7.dist-info/LICENSE
nifstd_tools-0.0.7.dist-info/METADATA
nifstd_tools-0.0.7.dist-info/WHEEL
nifstd_tools-0.0.7.dist-info/entry_points.txt
nifstd_tools-0.0.7.dist-info/top_level.txt
nifstd_tools-0.0.7.dist-info/RECORD
