Metadata-Version: 2.1
Name: nifstd-tools
Version: 0.0.7
Summary: utilities for working with the NIF ontology
Home-page: https://github.com/tgbugs/pyontutils/tree/master/nifstd
Author: Tom Gillespie
Author-email: tgbugs@gmail.com
License: MIT
Keywords: nif nifstd ontology pyontutils neuroscience
Classifier: Development Status :: 4 - Beta
Classifier: License :: OSI Approved :: MIT License
Classifier: Programming Language :: Python :: 3.6
Classifier: Programming Language :: Python :: 3.7
Classifier: Programming Language :: Python :: 3.8
Classifier: Programming Language :: Python :: 3.9
Classifier: Programming Language :: Python :: 3.10
Classifier: Programming Language :: Python :: 3.11
Requires-Python: >=3.6
License-File: LICENSE
Requires-Dist: beautifulsoup4
Requires-Dist: flask
Requires-Dist: nbconvert
Requires-Dist: nbformat
Requires-Dist: networkx
Requires-Dist: psutil
Requires-Dist: pymysql
Requires-Dist: pyontutils (>=0.1.26)
Requires-Dist: sqlalchemy
Provides-Extra: dev
Requires-Dist: mysql-connector ; extra == 'dev'
Requires-Dist: protobuf ; extra == 'dev'
Requires-Dist: pytest-cov ; extra == 'dev'
Requires-Dist: wheel ; extra == 'dev'
Provides-Extra: spell
Requires-Dist: hunspell ; extra == 'spell'
Provides-Extra: test
Requires-Dist: pytest ; extra == 'test'
